setup.py
pga/__init__.py
pga.basemodel.egg-info/PKG-INFO
pga.basemodel.egg-info/SOURCES.txt
pga.basemodel.egg-info/dependency_links.txt
pga.basemodel.egg-info/namespace_packages.txt
pga.basemodel.egg-info/not-zip-safe
pga.basemodel.egg-info/top_level.txt
pga/basemodel/__init__.py
pga/basemodel/mixin.py