Metadata-Version: 1.0
Name: pga.basemodel
Version: 0.3
Summary: Columns that should be in every Postgresql SQLAlchemy model. Used as a mixin. Support Postgres only.
Home-page: http://github.com/pgallen90/basemodel
Author: Patrick Allen
Author-email: patrickgallen@gmail.com
License: MIT
Platform: UNKNOWN
